{"status": "ok", "totalResults": 1, "articles": [{"source": {"id": "al-jazeera-english", "name": "Al Jazeera English"}, "author": "Hafsa Adil", "title": "Qatar keep AFC Asian Cup trophy at home with 3-1 win over Jordan - Al Jazeera English", "description": "Qatar became the first country in 20 years to win back-to-back Asian Cup titles with a 3-1 win over Jordan.", "url": "https://www.aljazeera.com/sports/2024/2/11/qatar-keep-afc-asian-cup-trophy-at-home-with-3-1-win-over-jordan", "urlToImage": "https://www.aljazeera.com/wp-content/uploads/2024/02/2024-02-10T174721Z_1504982070_UP1EK2A1DEU92_RTRMADP_3_SOCCER-ASIANCUP-JOR-QAT-REPORT-1707632601.jpg?resize=1920%2C1440", "publishedAt": "2024-02-11T06:37:49Z", "content": "Lusail Stadium, Qatar The worlds eyes were on the majestic Lusail Stadium once again as it played host to another historic final that saw hosts Qatar hold on to their Asian Cup crown against first-ti\u2026 [+5415 chars]"}]}