{"status": "ok", "totalResults": 1, "articles": [{"source": {"id": null, "name": "BBC News"}, "author": null, "title": "Wendy Williams thanks fans for support after dementia and aphasia diagnosis - BBC.com", "description": "The talk show host says she feels \"immense gratitude\" for the supportive messages sent to her.", "url": "https://www.bbc.com/news/entertainment-arts-68391330", "urlToImage": "https://ichef.bbci.co.uk/news/1024/branded_news/5C1E/production/_132728532_gettyimages-1181706364.jpg", "publishedAt": "2024-02-24T17:25:29Z", "content": "By Charlotte GallagherCulture correspondent\r\nWendy Williams says she continues to need \"personal space and peace to thrive\"\r\nFormer US talk show host Wendy Williams has thanked fans for their support\u2026 [+2021 chars]"}]}