{"status": "ok", "totalResults": 1, "articles": [{"source": {"id": null, "name": "VOA News"}, "author": "Associated Press", "title": "Don't expect human life expectancy to grow much more, researcher says - VOA Asia", "description": "Medical advances, genetic research aren\u2019t translating into overall jumps in lifespans", "url": "https://www.voanews.com/a/don-t-expect-human-life-expectancy-to-grow-much-more-researcher-says-/7813894.html", "urlToImage": "https://gdb.voanews.com/DDD4E9F2-2203-4DFB-8838-576D4BD2187D.jpg", "publishedAt": "2024-10-08T00:37:45Z", "content": "new york \u00a0Humanity is hitting the upper limit of life expectancy, according to a new study.\r\nAdvances in medical technology and genetic research not to mention larger numbers of people making it to a\u2026 [+3658 chars]"}]}