{"status": "ok", "totalResults": 1, "articles": [{"source": {"id": null, "name": "SciTechDaily"}, "author": null, "title": "\u201cHomo juluensis\u201d: Scientists Claim To Have Discovered New Species of Humans - SciTechDaily", "description": "Researcher Christopher J. Bae identified Homo juluensis, a new human species that coexisted with Denisovans in Asia. A University of Hawai\u02bbi researcher may have identified a new human species, Homo juluensis, which could encompass enigmatic groups like the De\u2026", "url": "https://scitechdaily.com/homo-juluensis-scientists-claim-to-have-discovered-new-species-of-humans/", "urlToImage": "https://scitechdaily.com/images/Primitive-Humans-Cavemen-Neanderthals.jpg", "publishedAt": "2025-01-05T11:33:26Z", "content": "A new human species, Homo juluensis, has been proposed based on fossils from eastern Asia, dating back 300,000 to 50,000 years ago, possibly including the Denisovans. This research uses a novel metho\u2026 [+3230 chars]"}]}