{"status": "ok", "totalResults": 2, "articles": [{"source": {"id": null, "name": "CNBC"}, "author": "Jihye Lee, Lim Hui Jie", "title": "Asia markets slide further in early trading as Wall Street pauses market rally - CNBC", "description": "Investors in the region also further assessed economic data that has been released this week.", "url": "https://www.cnbc.com/2023/06/08/asia-markets.html", "urlToImage": "https://image.cnbcfm.com/api/v1/image/102144646-178236410.jpg?v=1686181394&w=1920&h=1080", "publishedAt": "2023-06-08T01:25:00Z", "content": "Asia-Pacific markets slid as Wall Street saw a pause in its market rally and the broad market index fluctuated near its highest closing levels since August 2022. Investors in the region also further \u2026 [+1521 chars]"}]}