{"status": "ok", "totalResults": 1, "articles": [{"source": {"id": null, "name": "VOA News"}, "author": "Anita Powell", "title": "Biden hits Germany with lightning-quick visit focused on Middle East, Ukraine - VOA Asia", "description": "The US president make an in-person push for transatlantic unity and scoops up Germany\u2019s highest civilian honor", "url": "https://www.voanews.com/a/biden-hits-germany-with-lightning-quick-visit-focused-on-middle-east-ukraine/7827478.html", "urlToImage": "https://gdb.voanews.com/1025B6DE-97D5-4A3F-A680-D0B134B0E077.jpg", "publishedAt": "2024-10-18T14:24:56Z", "content": "Berlin \u00a0President Joe Biden made a lightning-fast, pomp-filled visit to Germany Friday, making an in-person push for transatlantic unity and scooping up Germanys highest civilian honor.\r\nBiden also m\u2026 [+3490 chars]"}]}