{"status": "ok", "totalResults": 1, "articles": [{"source": {"id": null, "name": "The Star Online"}, "author": "The Star Online", "title": "AirAsia completes RM974.5mil rights issue - The Star Online", "description": "KUALA LUMPUR: AirAsia Group Bhd is expected to complete its renounceable rights issue to its existing shareholders upon the listing of the redeemable convertible unsecured Islamic debt securities (RCUIDS) and warrants on Dec 31.", "url": "https://www.thestar.com.my/business/business-news/2021/12/29/airasia-completes-rm9745mil-rights-issue", "urlToImage": "https://apicms.thestar.com.my/uploads/images/2021/12/29/1423670.JPG", "publishedAt": "2021-12-29T02:23:00Z", "content": "KUALA LUMPUR: AirAsia Group Bhd is expected to complete its renounceable rights issue to its existing shareholders upon the listing of the redeemable convertible unsecured Islamic debt securities (RC\u2026 [+2349 chars]"}]}