{"status": "ok", "totalResults": 1, "articles": [{"source": {"id": null, "name": "Phys.Org"}, "author": "CSIRO", "title": "New species of deep-sea shark and crab discovered off Western Australia - Phys.org", "description": "Researchers have described a new species of deep-sea lanternshark and crab, both with the help of specimens collected from a CSIRO-led 2022 voyage of CSIRO research vessel (RV) Investigator.", "url": "https://phys.org/news/2025-10-species-deep-sea-shark-crab.html", "urlToImage": "https://scx2.b-cdn.net/gfx/news/2025/new-species-of-deep-se-1.jpg", "publishedAt": "2025-10-06T15:28:18Z", "content": "Researchers have described a new species of deep-sea lanternshark and crab, both with the help of specimens collected from a CSIRO-led 2022 voyage of CSIRO research vessel (RV) Investigator.\r\nCalled \u2026 [+4409 chars]"}]}