{"status": "ok", "totalResults": 2, "articles": [{"source": {"id": null, "name": "ScienceAlert"}, "author": "ScienceAlert Staff", "title": "Man Keeps Rock For Years Thinking It's Gold. It Turned Out to Be Far More Valuable. - ScienceAlert", "description": "In 2015, David Hole was prospecting in Maryborough Regional Park near Melbourne, Australia.", "url": "https://www.sciencealert.com/man-keeps-rock-for-years-thinking-its-gold-it-turned-out-to-be-far-more-valuable", "urlToImage": "https://www.sciencealert.com/images/2022/11/TheMaryboroughRock.jpg", "publishedAt": "2023-11-23T23:25:44Z", "content": "In 2015, David Hole was prospecting in Maryborough Regional Park near Melbourne, Australia.\r\nArmed with a metal detector, he discovered something out of the ordinary a very heavy, reddish rock restin\u2026 [+4381 chars]"}]}