{"status": "ok", "totalResults": 1, "articles": [{"source": {"id": null, "name": "ATP Tour"}, "author": null, "title": "Alcaraz, Djokovic & Nadal congratulate Sinner on Australian Open title - ATP Tour", "description": "Carlos Alcaraz, Novak Djokovic and Rafael Nadal were among the players who took to social media Sunday to congratulate Jannik Sinner on his Australian Open triumph.", "url": "https://www.atptour.com/en/news/sinner-australian-open-2025-social-media-reaction", "urlToImage": "https://www.atptour.com/-/media/images/news/2025/01/26/12/36/sinner-australian-open-2025-trophy-high-view.jpg", "publishedAt": "2025-01-26T12:51:42Z", "content": null}]}