{"status": "ok", "totalResults": 1, "articles": [{"source": {"id": null, "name": "BBC News"}, "author": null, "title": "New Caledonia: Australia and New Zealand send evacuation flights amid unrest - BBC.com", "description": "The French Pacific territory's airport has been closed since deadly unrest erupted last week.", "url": "https://www.bbc.com/news/articles/crgg821ezz8o", "urlToImage": "https://ichef.bbci.co.uk/news/1024/branded_news/c90a/live/591858c0-1713-11ef-b71c-3b126590418b.jpg", "publishedAt": "2024-05-21T09:58:09Z", "content": null}]}