{"status": "ok", "totalResults": 1, "articles": [{"source": {"id": null, "name": "YouTube"}, "author": null, "title": "Calls for free flu vaccines in Queensland as Influenza B outbreak rips through the state | 7NEWS - 7NEWS Australia", "description": "There are calls for the flu vaccine to be made free for all Queenslanders again this year as an outbreak of influenza B rips through the state.Many children ...", "url": "https://www.youtube.com/watch?v=JQr6LMF_Qi4", "urlToImage": "https://i.ytimg.com/vi/JQr6LMF_Qi4/hqdefault.jpg", "publishedAt": "2023-07-14T08:28:09Z", "content": null}]}