{"status": "ok", "totalResults": 1, "articles": [{"source": {"id": null, "name": "BBC News"}, "author": null, "title": "King Charles's Australia tour - and why it nearly did not happen - BBC.com", "description": "Eight months after his cancer diagnosis was revealed, this royal tour is important for Charles - and the monarchy.", "url": "https://www.bbc.com/news/articles/c93y2r75ky7o", "urlToImage": "https://ichef.bbci.co.uk/news/1024/branded_news/f953/live/b51c57c0-8a13-11ef-81f8-1f28bcc5be15.jpg", "publishedAt": "2024-10-18T17:28:59Z", "content": "King Charles III and Queen Camilla are due to arrive in Australia on Friday on a historic royal tour. \r\nEight months ago, I didnt think Id be writing those words.\r\nIn February, Buckingham Palace anno\u2026 [+5376 chars]"}]}