{"status": "ok", "totalResults": 1, "articles": [{"source": {"id": null, "name": "Newser"}, "author": "Arden Dier", "title": "He Died From a Bat Bite. It Wasn't Rabies - Newser", "description": "Fourth human case of Australian bat lyssavirus proves fatal in New South Wales", "url": "https://www.newser.com/story/371329/he-died-from-a-bat-bite-it-wasnt-rabies.html", "urlToImage": "https://img1-azrcdn.newser.com/image/1620194-12-20250703103231.jpeg", "publishedAt": "2025-07-03T15:14:00Z", "content": "An Australian man has died after becoming just the fourth known person to contract an extremely rare, bat-borne virus. Australian bat lyssavirus (ABLV)\u2014unique to Australia, where it was first identif\u2026 [+1175 chars]"}]}